odoo/addons/product_brand_mrp/README.rst
odoo/addons/product_brand_mrp/__init__.py
odoo/addons/product_brand_mrp/__manifest__.py
odoo/addons/product_brand_mrp/i18n/it.po
odoo/addons/product_brand_mrp/i18n/nl.po
odoo/addons/product_brand_mrp/i18n/product_brand_mrp.pot
odoo/addons/product_brand_mrp/models/__init__.py
odoo/addons/product_brand_mrp/models/mrp_production.py
odoo/addons/product_brand_mrp/readme/CONTRIBUTORS.md
odoo/addons/product_brand_mrp/readme/DESCRIPTION.md
odoo/addons/product_brand_mrp/readme/USAGE.md
odoo/addons/product_brand_mrp/static/description/icon.png
odoo/addons/product_brand_mrp/static/description/index.html
odoo/addons/product_brand_mrp/tests/__init__.py
odoo/addons/product_brand_mrp/tests/test_product_brand_mrp.py
odoo/addons/product_brand_mrp/views/mrp_production_views.xml
odoo_addon_product_brand_mrp-18.0.1.0.0.4.dist-info/METADATA
odoo_addon_product_brand_mrp-18.0.1.0.0.4.dist-info/WHEEL
odoo_addon_product_brand_mrp-18.0.1.0.0.4.dist-info/top_level.txt
odoo_addon_product_brand_mrp-18.0.1.0.0.4.dist-info/RECORD
