Metadata-Version: 2.1
Name: odoo-addon-product_brand_mrp
Version: 18.0.1.0.0.4
Requires-Python: >=3.10
Requires-Dist: odoo-addon-product_brand==18.0.*
Requires-Dist: odoo==18.0.*
Summary: This module allows to work with product_brand in MRP.
Home-page: https://github.com/OCA/brand
License: AGPL-3
Author: Odoo Community Association (OCA)
Author-email: support@odoo-community.org
Classifier: Programming Language :: Python
Classifier: Framework :: Odoo
Classifier: Framework :: Odoo :: 18.0
Classifier: License :: OSI Approved :: GNU Affero General Public License v3
